nataly/__init__.py
nataly/chart.py
nataly/config.py
nataly/constants.py
nataly/core.py
nataly/engine.py
nataly/layout.py
nataly/models.py
nataly/utils.py
nataly-0.1.6.dist-info/licenses/LICENSE
tests/__init__.py
tests/references.py
tests/test_core.py
tests/test_nataly_library.py
tests/test_reference.py
tests/test_utils.py
nataly-0.1.6.dist-info/METADATA
nataly-0.1.6.dist-info/WHEEL
nataly-0.1.6.dist-info/top_level.txt
nataly-0.1.6.dist-info/RECORD
